crowsay/__init__.py
crowsay/__main__.py
crowsay-1.2.dist-info/LICENSE
crowsay-1.2.dist-info/METADATA
crowsay-1.2.dist-info/WHEEL
crowsay-1.2.dist-info/top_level.txt
crowsay-1.2.dist-info/RECORD
